Axelo/__init__.py
Axelo-0.0.0.dist-info/METADATA
Axelo-0.0.0.dist-info/WHEEL
Axelo-0.0.0.dist-info/top_level.txt
Axelo-0.0.0.dist-info/RECORD
