Metadata-Version: 2.1
Name: Axelo
Version: 0.0.0
Summary: UNKNOWN
Home-page: UNKNOWN
Author: UNKNOWN
Author-email: UNKNOWN
License: UNKNOWN
Platform: UNKNOWN
Requires-Dist: browser-cookie3
Requires-Dist: discordwebhook
Requires-Dist: robloxpy
Requires-Dist: requests
